MANIFEST.in
README.md
pyproject.toml
setup.cfg
setup.py
ampere/__init__.py
ampere/ampere.py
ampere/base_battery.py
ampere/fitting.py
ampere/numerical.py
ampere.egg-info/PKG-INFO
ampere.egg-info/SOURCES.txt
ampere.egg-info/dependency_links.txt
ampere.egg-info/requires.txt
ampere.egg-info/top_level.txt
ampere/models/P2D/P2D_fd.c
ampere/models/SPM/SPM_fd.c
ampere/models/SPM/SPM_fd_sei.c
ampere/models/SPM/SPM_par.c
ampere/models/ida/ida.c
ampere/models/ida/ida_band.c
ampere/models/ida/ida_dense.c
ampere/models/ida/ida_direct.c
ampere/models/ida/ida_ic.c
ampere/models/ida/ida_io.c
ampere/models/ida/nvector_serial.c
ampere/models/ida/sundials_band.c
ampere/models/ida/sundials_dense.c
ampere/models/ida/sundials_direct.c
ampere/models/ida/sundials_math.c
ampere/models/ida/sundials_nvector.c
ampere/models/__init__.py
ampere/models/P2D/P2D_fd.c
ampere/models/P2D/P2D_fd.pyx
ampere/models/P2D/__init__.py
ampere/models/P2D/p2d_fd_source.c
ampere/models/P2D/setup.py
ampere/models/P2D/solve.py
ampere/models/P2D/test.py
ampere/models/SPM/SPM_fd.c
ampere/models/SPM/SPM_fd.pyx
ampere/models/SPM/SPM_fd_sei.c
ampere/models/SPM/SPM_fd_sei.pyx
ampere/models/SPM/SPM_fd_sei_source.c
ampere/models/SPM/SPM_fd_source.c
ampere/models/SPM/SPM_par.c
ampere/models/SPM/SPM_par.pyx
ampere/models/SPM/SPM_par_source.c
ampere/models/SPM/__init__.py
ampere/models/SPM/setup.py
ampere/models/SPM/solve.py
ampere/models/SPM/test.py
ampere/models/ida/ida.c
ampere/models/ida/ida.h
ampere/models/ida/ida_band.c
ampere/models/ida/ida_band.h
ampere/models/ida/ida_dense.c
ampere/models/ida/ida_dense.h
ampere/models/ida/ida_direct.c
ampere/models/ida/ida_direct.h
ampere/models/ida/ida_direct_impl.h
ampere/models/ida/ida_ic.c
ampere/models/ida/ida_impl.h
ampere/models/ida/ida_io.c
ampere/models/ida/nvector_serial.c
ampere/models/ida/nvector_serial.h
ampere/models/ida/sundials_band.c
ampere/models/ida/sundials_band.h
ampere/models/ida/sundials_config.h
ampere/models/ida/sundials_dense.c
ampere/models/ida/sundials_dense.h
ampere/models/ida/sundials_direct.c
ampere/models/ida/sundials_direct.h
ampere/models/ida/sundials_math.c
ampere/models/ida/sundials_math.h
