Metadata-Version: 2.1
Name: ampere
Version: 0.5.6
Summary: A Python package for working with battery discharge data and physics-based battery models
Home-page: https://github.com/nealde/Ampere
Author: Neal Dawson-Elli
Author-email: nealde@uw.edu
License: UNKNOWN
Keywords: battery numerical simulation modeling
Platform: UNKNOWN
Classifier: Programming Language :: Python :: 3
Classifier: Programming Language :: Cython
Classifier: License :: OSI Approved :: MIT License
Classifier: Operating System :: OS Independent
Classifier: Topic :: Scientific/Engineering :: Mathematics
